gnomes_at_night_gym/__init__.py
gnomes_at_night_gym/envs/__init__.py
gnomes_at_night_gym/envs/gnomesAtNightEnv_5A.py
gnomes_at_night_gym/envs/gnomesAtNightEnv_9A.py
gnomes_at_night_gym/envs/gnomesAtNightEnv_9_multistep.py
gnomes_at_night_gym/envs/maze_layouts/0000.json
gnomes_at_night_gym/envs/maze_layouts/0001.json
gnomes_at_night_gym/envs/maze_layouts/0002.json
gnomes_at_night_gym/envs/maze_layouts/0003.json
gnomes_at_night_gym-0.0.11.dist-info/METADATA
gnomes_at_night_gym-0.0.11.dist-info/WHEEL
gnomes_at_night_gym-0.0.11.dist-info/top_level.txt
gnomes_at_night_gym-0.0.11.dist-info/RECORD
